facework/FaceCrop.py
facework/FaceMorph.py
facework/__init__.py
facework-0.1.1.dist-info/licenses/LICENSE
facework-0.1.1.dist-info/METADATA
facework-0.1.1.dist-info/WHEEL
facework-0.1.1.dist-info/top_level.txt
facework-0.1.1.dist-info/RECORD
