Metadata-Version: 2.4
Name: facework
Version: 0.1.1
Summary: A Python library for face cropping and face morphing
Author-email: Gioele Angelo Crespi <crespigioeleangelo@email.com>
License: MIT
Project-URL: Homepage, https://github.com/gngcr/FaceWork
Project-URL: Repository, https://github.com/gngcr/FaceWork
Keywords: face,morph,crop,image-processing,computer-vision,landmark-detection
Requires-Python: >=3.10.11
License-File: LICENSE
Requires-Dist: ffmpeg-python==0.2.0
Requires-Dist: matplotlib==3.10.1
Requires-Dist: mediapipe==0.10.21
Requires-Dist: numpy
Requires-Dist: opencv-contrib-python==4.11.0.86
Requires-Dist: opencv-python==4.11.0.86
Requires-Dist: pandas
Requires-Dist: pillow==11.1.0
Requires-Dist: psutil==7.0.0
Requires-Dist: scipy==1.15.2
Requires-Dist: Wand==0.6.13
Dynamic: license-file
